.gitignore
LICENSE.txt
MANIFEST.in
README.md
requirements.txt
setup.py
crypto_payments.egg-info/PKG-INFO
crypto_payments.egg-info/SOURCES.txt
crypto_payments.egg-info/dependency_links.txt
crypto_payments.egg-info/not-zip-safe
crypto_payments.egg-info/requires.txt
crypto_payments.egg-info/top_level.txt
merchant_wallet/__init__.py
merchant_wallet/__version__.py
merchant_wallet/backends/__init__.py
merchant_wallet/backends/btc.py
merchant_wallet/tests/__init__.py
merchant_wallet/tests/test_btc_backend.py