Metadata-Version: 2.1
Name: crypto-payments
Version: 1.1.2
Summary: Receive cryptocurrency payment, generate hd cryptocurrency wallet addresses and verifying payment made to an address.
Home-page: https://github.com/ydaniels/HD-Merchant-wallet
Author: halt
Author-email: yomidall@gmail.com
License: MIT
Keywords: electrum web network internet btc bitcoin blockchain hd wallet crptocurrency crypto merchant
Platform: UNKNOWN
Classifier: License :: OSI Approved :: MIT License
Classifier: Programming Language :: Python :: 3.6
